seep/__init__.py
seep/core.py
seep/tests/__init__.py
seep/tests/test_core.py
seep-0.3.0.dist-info/COPYING
seep-0.3.0.dist-info/METADATA
seep-0.3.0.dist-info/WHEEL
seep-0.3.0.dist-info/top_level.txt
seep-0.3.0.dist-info/RECORD
